uwosh.oie.studyabroadtheme-1.0-py2.7-nspkg.pth
uwosh/.DS_Store
uwosh/oie/.DS_Store
uwosh/oie/studyabroadtheme/.DS_Store
uwosh/oie/studyabroadtheme/__init__.py
uwosh/oie/studyabroadtheme/configure.zcml
uwosh/oie/studyabroadtheme/interfaces.py
uwosh/oie/studyabroadtheme/setuphandlers.py
uwosh/oie/studyabroadtheme/testing.py
uwosh/oie/studyabroadtheme/browser/__init__.py
uwosh/oie/studyabroadtheme/browser/configure.zcml
uwosh/oie/studyabroadtheme/browser/overrides/.gitkeep
uwosh/oie/studyabroadtheme/browser/static/.gitkeep
uwosh/oie/studyabroadtheme/locales/update.sh
uwosh/oie/studyabroadtheme/locales/uwosh.oie.studyabroadtheme.pot
uwosh/oie/studyabroadtheme/profiles/default/browserlayer.xml
uwosh/oie/studyabroadtheme/profiles/default/metadata.xml
uwosh/oie/studyabroadtheme/profiles/default/registry.xml
uwosh/oie/studyabroadtheme/profiles/default/theme.xml
uwosh/oie/studyabroadtheme/profiles/uninstall/browserlayer.xml
uwosh/oie/studyabroadtheme/profiles/uninstall/theme.xml
uwosh/oie/studyabroadtheme/tests/__init__.py
uwosh/oie/studyabroadtheme/tests/test_robot.py
uwosh/oie/studyabroadtheme/tests/test_setup.py
uwosh/oie/studyabroadtheme/tests/robot/test_example.robot
uwosh/oie/studyabroadtheme/theme/.DS_Store
uwosh/oie/studyabroadtheme/theme/favicon.ico
uwosh/oie/studyabroadtheme/theme/grid.xml
uwosh/oie/studyabroadtheme/theme/index.html
uwosh/oie/studyabroadtheme/theme/manifest.cfg
uwosh/oie/studyabroadtheme/theme/preview.png
uwosh/oie/studyabroadtheme/theme/rules.xml
uwosh/oie/studyabroadtheme/theme/css/bootstrap-theme.css
uwosh/oie/studyabroadtheme/theme/css/bootstrap-theme.min.css
uwosh/oie/studyabroadtheme/theme/css/bootstrap.css
uwosh/oie/studyabroadtheme/theme/css/bootstrap.min.css
uwosh/oie/studyabroadtheme/theme/css/bs.min.css
uwosh/oie/studyabroadtheme/theme/css/oie.css
uwosh/oie/studyabroadtheme/theme/css/uwo-diazo-tweaks.css
uwosh/oie/studyabroadtheme/theme/fonts/glyphicons-halflings-regular.eot
uwosh.oie.studyabroadtheme-1.0.dist-info/LICENSE
uwosh.oie.studyabroadtheme-1.0.dist-info/LICENSE.GPL
uwosh.oie.studyabroadtheme-1.0.dist-info/LICENSE.rst
uwosh.oie.studyabroadtheme-1.0.dist-info/METADATA
uwosh.oie.studyabroadtheme-1.0.dist-info/WHEEL
uwosh.oie.studyabroadtheme-1.0.dist-info/entry_points.txt
uwosh.oie.studyabroadtheme-1.0.dist-info/namespace_packages.txt
uwosh.oie.studyabroadtheme-1.0.dist-info/top_level.txt
uwosh.oie.studyabroadtheme-1.0.dist-info/RECORD
