Metadata-Version: 2.1
Name: uwosh.oie.studyabroadtheme
Version: 1.0
Summary: Plone theme for UW Oshkosh Office of International Education
Home-page: https://pypi.python.org/pypi/uwosh.oie.studyabroadtheme
Author: T. Kim Nguyen
Author-email: kim.nguyen@wildcardcorp.com
License: GPL version 2
Keywords: Python Plone
Platform: UNKNOWN
Classifier: Environment :: Web Environment
Classifier: Framework :: Plone
Classifier: Framework :: Plone :: 5.0
Classifier: Framework :: Plone :: 5.1
Classifier: Programming Language :: Python
Classifier: Programming Language :: Python :: 2.7
Classifier: Operating System :: OS Independent
Classifier: License :: OSI Approved :: GNU General Public License v2 (GPLv2)
Requires-Dist: plone.api
Requires-Dist: Products.GenericSetup (>=1.8.2)
Requires-Dist: setuptools
Requires-Dist: z3c.jbot
Requires-Dist: plone.app.theming
Requires-Dist: plone.app.themingplugins
Provides-Extra: test
Requires-Dist: plone.app.testing ; extra == 'test'
Requires-Dist: plone.testing (>=5.0.0) ; extra == 'test'
Requires-Dist: plone.app.contenttypes ; extra == 'test'
Requires-Dist: plone.app.robotframework[debug] ; extra == 'test'
